Metadata-Version: 2.1
Name: moascode-probability
Version: 0.2
Summary: ['Gaussian and Binomial distributions']
Author: moascode
